LICENSE
README.md
setup.py
zoho_client/__init__.py
zoho_client/admin.py
zoho_client/apps.py
zoho_client/models.py
zoho_client/tests.py
zoho_client/views.py
zoho_client/zoho.py
zoho_client/migrations/0001_initial.py
zoho_client/migrations/__init__.py
zoho_client/templates/admin/zoho_client/zohotoken/fetch_tokens.html
zoho_client/templates/admin/zoho_client/zohotoken/zoho_token_change_list.html
zoho_client_django.egg-info/PKG-INFO
zoho_client_django.egg-info/SOURCES.txt
zoho_client_django.egg-info/dependency_links.txt
zoho_client_django.egg-info/requires.txt
zoho_client_django.egg-info/top_level.txt
zoho_test_project/__init__.py
zoho_test_project/asgi.py
zoho_test_project/settings.py
zoho_test_project/urls.py
zoho_test_project/wsgi.py