Metadata-Version: 2.1
Name: zoho-client-django
Version: 1.2.0
Summary: Django app which is a client for the Zoho CRM API
Home-page: https://github.com/gosourcellc/zoho-client-django
Author: Guy Moller
Author-email: guy.moller@gmail.com
License: UNKNOWN
Platform: UNKNOWN
License-File: LICENSE
